{
    "assets": {
        "band-0": {
            "href": "https://pta.data.lit.fmi.fi/sen1/s1_grd_vh_prep/S1_processed_20190113_051104_051224_014471_01AF2B_VH.tif", 
            "type": "image/vnd.stac.geotiff; cloud-optimized=true", 
            "title": "Band 0"
        }, 
        "band-1": {
            "href": "https://pta.data.lit.fmi.fi/sen1/s1_grd_vv_prep/S1_processed_20190113_051104_051224_014471_01AF2B_VV.tif", 
            "type": "image/vnd.stac.geotiff; cloud-optimized=true", 
            "title": "Band 1"
        }
    }, 
    "links": [
        {
            "href": "https://stac.fmi.fi/stac/catalog/S1_processed_20190113_051104_051224_014471_01AF2B.dim.json", 
            "rel": "self"
        }
    ], 
    "geometry": {
        "type": "Polygon", 
        "coordinates": [
            [
                [
                    14.82826, 
                    71.93484
                ], 
                [
                    17.467907, 
                    66.740402
                ], 
                [
                    26.443143, 
                    67.02735
                ], 
                [
                    26.284732, 
                    72.314324
                ], 
                [
                    14.82826, 
                    71.93484
                ]
            ]
        ]
    }, 
    "id": "S1_processed_20190113_051104_051224_014471_01AF2B", 
    "bbox": [
        14.828259732740474, 
        66.74040150143293, 
        26.443143485422418, 
        72.31432394396785
    ], 
    "type": "Feature", 
    "properties": {
        "dtr:start_datetime": "2019-01-13T05:11:06.380832Z", 
        "title": "BEAM-PRODUCT", 
        "dtr:end_datetime": "2019-01-13T05:12:24.345319Z", 
        "datetime": "2019-01-13T05:11:06.380832Z"
    }
}